link_crab/__init__.py
link_crab/__main__.py
link_crab/csv_reader.py
link_crab/exercise_url.py
link_crab/gather_links.py
link_crab/reporting.py
link_crab/session_manager.py
tests/__init__.py
tests/test_app.py
tests/test_excercise_url.py
tests/test_gather_links.py
tests/test_helpers.py
tests/test_session_manager.py
link_crab-0.2.1.dist-info/LICENCE
link_crab-0.2.1.dist-info/METADATA
link_crab-0.2.1.dist-info/WHEEL
link_crab-0.2.1.dist-info/top_level.txt
link_crab-0.2.1.dist-info/RECORD
