Metadata-Version: 2.1
Name: link-crab
Version: 0.2.1
Summary: A link crawler and permission testing tool for websites
Home-page: https://github.com/klucsik/link-crab
Author: Krisztián Pál Klucsik
Author-email: klucsik.krisztian@gmail.com
License: UNKNOWN
Platform: UNKNOWN
Classifier: Programming Language :: Python :: 3
Classifier: License :: OSI Approved :: MIT License
Classifier: Operating System :: OS Independent
Requires-Python: >=3.6
Requires-Dist: beautifulsoup4
Requires-Dist: colorama
Requires-Dist: Flask
Requires-Dist: Flask-user
Requires-Dist: Flask-babelex
Requires-Dist: email-validator
Requires-Dist: PyYAML
Requires-Dist: requests
Requires-Dist: selenium
Requires-Dist: pytest
